<?xml version="1.0" encoding="ISO-8859-1"?>

<PropertyList>

  <!-- Les sièges -->
  <!-- Pilote -->
  <model>
    <path>Aircraft/Douglas-Dc3/Models/Interior/Cockpit/seats/pilot-seat.xml</path>
    <offsets>
      <x-m>  0.516 </x-m>
      <y-m> -0.500 </y-m>
      <z-m> -0.405 </z-m>
    </offsets>
  </model>

  <!-- Copilote -->
  <model>
    <path>Aircraft/Douglas-Dc3/Models/Interior/Cockpit/seats/pilot-seat.xml</path>
    <offsets>
      <x-m>  0.516 </x-m>
      <y-m>  0.500 </y-m>
      <z-m> -0.405 </z-m>
    </offsets>
  </model>

</PropertyList>
